algomax/__init__.py
algomax/__main__.py
algomax/algomax.py
algomax/messages.py
algomax/schedule_type.py
algomax/scheduler.py
algomax/user_schedule_data.py
algomax/utils.py
algomax-0.3.1.dist-info/LICENSE
algomax-0.3.1.dist-info/METADATA
algomax-0.3.1.dist-info/WHEEL
algomax-0.3.1.dist-info/entry_points.txt
algomax-0.3.1.dist-info/top_level.txt
algomax-0.3.1.dist-info/RECORD
