Metadata-Version: 2.1
Name: algomax
Version: 0.3.1
Summary: cli tool for write your own trade algorithms
Home-page: https://mabnadp.com
Author: hadi.f
Author-email: h.farhadi@mabnadp.com
License: UNKNOWN
Keywords: algomax EMAX trader cli-trader algomax-cli
Platform: UNKNOWN
Classifier: Programming Language :: Python :: 3
Classifier: License :: OSI Approved :: MIT License
Classifier: Operating System :: OS Independent
Requires-Python: >=3.6
Requires-Dist: click (==7.0.0)
Requires-Dist: schedule (==0.6.0)
Requires-Dist: pyfiglet (==0.8.post1)
Requires-Dist: algomax-common (==0.2)
